{
	"name": "Story 2",
	"description": "Lorem ipsum dolor sit amet, consectetur adipiscing elit. Proin nisl tortor, tincidunt eget vehicula quis, viverra vel nulla. Etiam vehicula urna eget ipsum tincidunt, at blandit magna facilisis. Ut vehicula purus at enim suscipit, a lobortis lacus dignissim. In sollicitudin consequat ultricies. Morbi vitae lorem quis tellus malesuada aliquet in a augue. Nunc ultricies, odio quis tincidunt tincidunt, augue augue tincidunt velit, in semper sapien quam at nisi. Nulla scelerisque dui quis lectus suscipit laoreet. Donec ex est, pellentesque vel blandit vitae, facilisis non felis. Maecenas nec eros vel augue pharetra cursus. Ut sollicitudin, tortor quis vestibulum placerat, dolor nunc tempor ex, sit amet convallis velit dolor vel diam. ",
	"activities": [
		{
			"storyline": [
				["text", "Questo è un testo lunghissimo"],
				["text", "someText"]
			],
			"questions": [
				{
					"type": "someType",
					"answers": [
						{
							"value": "someText False False",
							"score": 0,
							"correct": false,
							"transition": false
						}
					],
					"tip": ["someText", "someText"]
				}
			]
		},
		{
			"storyline": [
				["image", "somePath"],
				["text", "Un altro testo lunghissimo"]
			],
			"questions": [
				{
					"type": "someType",
					"answers": [
						{
							"value": "someText",
							"score": 0,
							"correct": false,
							"transition": "someText"
						}
					],
					"tip": ["someText", "someText"]
				}
			]
		},
		{
			"storyline": [
				["text", "someText"],
				["image", "somePath"],
				["image", "somePath"],
				["text", "someText"]
			],
			"questions": [
				{
					"type": "someType",
					"answers": [
						{
							"value": "someText",
							"score": 0,
							"correct": false,
							"transition": "someText"
						}
					],
					"tip": ["someText", "someText"]
				}
			]
		},
		{
			"storyline": [
				["image", "somePath"],
				["text", "someText"]
			],
			"questions": [
				{
					"type": "someType",
					"answers": [
						{
							"value": "someText",
							"score": 0,
							"correct": false,
							"transition": "someText"
						}
					],
					"tip": ["someText", "someText"]
				}
			]
		}
	],
	"missions": {
		"0": {
			"0": [1],
			"1": [2],
			"2": [3],
			"3": ["new_mission"],
			"start": 0
		}
	},
	"transitions": ["0"]
}
